torch_specinv/__init__.py
torch_specinv/methods.py
torch_specinv/metrics.py
torch_specinv/utils.py
torch_specinv-0.1.dist-info/METADATA
torch_specinv-0.1.dist-info/WHEEL
torch_specinv-0.1.dist-info/top_level.txt
torch_specinv-0.1.dist-info/RECORD
