Metadata-Version: 2.1
Name: torch-specinv
Version: 0.1
Summary: A pytorch package for Spectrogram Inversion
Home-page: https://github.com/yoyololicon/spectrogram-inversion
Author: Chin-Yun Yu
Author-email: lolimaster.cs03@nctu.edu.tw
License: UNKNOWN
Platform: UNKNOWN
Classifier: Programming Language :: Python :: 3
Classifier: License :: OSI Approved :: MIT License
Classifier: Operating System :: OS Independent
Requires-Dist: torch (>=0.4.1)
Requires-Dist: tqdm
